ecoforest/__init__.py
ecoforest/config_function.py
ecoforest/src/__init__.py
ecoforest/src/hyperopt_nbeatsx.py
ecoforest/src/nbeats/__init__.py
ecoforest/src/nbeats/nbeats.py
ecoforest/src/nbeats/nbeats_model.py
ecoforest/src/nbeats/tcn.py
ecoforest/src/utils/__init__.py
ecoforest/src/utils/data/__init__.py
ecoforest/src/utils/data/utils.py
ecoforest/src/utils/data/datasets/__init__.py
ecoforest/src/utils/data/datasets/epf.py
ecoforest/src/utils/data/datasets/utils.py
ecoforest/src/utils/experiment/__init__.py
ecoforest/src/utils/experiment/utils_experiment.py
ecoforest/src/utils/numpyse/__init__.py
ecoforest/src/utils/numpyse/metrics.py
ecoforest/src/utils/pytorch/__init__.py
ecoforest/src/utils/pytorch/losses.py
ecoforest/src/utils/pytorch/ts_dataset.py
ecoforest/src/utils/pytorch/ts_loader.py
ecoforest-0.1.0.dist-info/METADATA
ecoforest-0.1.0.dist-info/WHEEL
ecoforest-0.1.0.dist-info/top_level.txt
ecoforest-0.1.0.dist-info/RECORD
