Metadata-Version: 2.1
Name: ecoforest
Version: 0.1.0
Summary: UNKNOWN
Home-page: UNKNOWN
Author: 
Author-email: 
License: UNKNOWN
Platform: UNKNOWN
Classifier: Programming Language :: Python :: 3
Classifier: License :: OSI Approved :: MIT License
Classifier: Operating System :: OS Independent
Requires-Dist: hyperopt (==0.2.5)
Requires-Dist: matplotlib (==3.3.3)
Requires-Dist: numpy (==1.18.5)
Requires-Dist: pandas (==1.1.5)
Requires-Dist: requests (==2.25.1)
Requires-Dist: scipy (==1.4.1)
Requires-Dist: statsmodels (==0.12.2)
Requires-Dist: torch (>=1.8.1)
Requires-Dist: tqdm (==4.54.1)
